{
  "__data_type": "UTC ",
  "Appearance_Type": {
    "type": "word",
    "value": 1794
  },
  "BodyBag": {
    "type": "byte",
    "value": 0
  },
  "Cha": {
    "type": "byte",
    "value": 8
  },
  "ChallengeRating": {
    "type": "float",
    "value": 25.0
  },
  "ClassList": {
    "type": "list",
    "value": [
      {
        "__struct_id": 2,
        "Class": {
          "type": "int",
          "value": 14
        },
        "ClassLevel": {
          "type": "short",
          "value": 5
        }
      },
      {
        "__struct_id": 2,
        "Class": {
          "type": "int",
          "value": 0
        },
        "ClassLevel": {
          "type": "short",
          "value": 22
        }
      },
      {
        "__struct_id": 2,
        "Class": {
          "type": "int",
          "value": 56
        },
        "ClassLevel": {
          "type": "short",
          "value": 5
        }
      }
    ]
  },
  "Comment": {
    "type": "cexostring",
    "value": ""
  },
  "Con": {
    "type": "byte",
    "value": 32
  },
  "Conversation": {
    "type": "resref",
    "value": ""
  },
  "CRAdjust": {
    "type": "int",
    "value": 0
  },
  "CurrentHitPoints": {
    "type": "short",
    "value": 4
  },
  "DecayTime": {
    "type": "dword",
    "value": 5000
  },
  "Deity": {
    "type": "cexostring",
    "value": ""
  },
  "Description": {
    "type": "cexolocstring",
    "value": {
      "0": "Powerfully built this Orc seems more viscious and stronger than the ones found in this area, he fights with a vicious abandon with very little thought but with pure strenght and ferocity."
    }
  },
  "Dex": {
    "type": "byte",
    "value": 24
  },
  "Disarmable": {
    "type": "byte",
    "value": 0
  },
  "Equip_ItemList": {
    "type": "list",
    "value": [
      {
        "__struct_id": 16,
        "Dropable": {
          "type": "byte",
          "value": 1
        },
        "EquippedRes": {
          "type": "resref",
          "value": "item040"
        }
      },
      {
        "__struct_id": 32,
        "Dropable": {
          "type": "byte",
          "value": 1
        },
        "EquippedRes": {
          "type": "resref",
          "value": "item036"
        }
      }
    ]
  },
  "FactionID": {
    "type": "word",
    "value": 1
  },
  "FeatList": {
    "type": "list",
    "value": [
      {
        "__struct_id": 1,
        "Feat": {
          "type": "word",
          "value": 1
        }
      },
      {
        "__struct_id": 1,
        "Feat": {
          "type": "word",
          "value": 490
        }
      },
      {
        "__struct_id": 1,
        "Feat": {
          "type": "word",
          "value": 194
        }
      },
      {
        "__struct_id": 1,
        "Feat": {
          "type": "word",
          "value": 328
        }
      },
      {
        "__struct_id": 1,
        "Feat": {
          "type": "word",
          "value": 408
        }
      },
      {
        "__struct_id": 1,
        "Feat": {
          "type": "word",
          "value": 1260
        }
      },
      {
        "__struct_id": 1,
        "Feat": {
          "type": "word",
          "value": 1259
        }
      },
      {
        "__struct_id": 1,
        "Feat": {
          "type": "word",
          "value": 1272
        }
      },
      {
        "__struct_id": 1,
        "Feat": {
          "type": "word",
          "value": 1271
        }
      },
      {
        "__struct_id": 1,
        "Feat": {
          "type": "word",
          "value": 1263
        }
      },
      {
        "__struct_id": 1,
        "Feat": {
          "type": "word",
          "value": 6
        }
      },
      {
        "__struct_id": 1,
        "Feat": {
          "type": "word",
          "value": 1310
        }
      },
      {
        "__struct_id": 1,
        "Feat": {
          "type": "word",
          "value": 334
        }
      },
      {
        "__struct_id": 1,
        "Feat": {
          "type": "word",
          "value": 1146
        }
      },
      {
        "__struct_id": 1,
        "Feat": {
          "type": "word",
          "value": 501
        }
      },
      {
        "__struct_id": 1,
        "Feat": {
          "type": "word",
          "value": 9
        }
      },
      {
        "__struct_id": 1,
        "Feat": {
          "type": "word",
          "value": 10
        }
      },
      {
        "__struct_id": 1,
        "Feat": {
          "type": "word",
          "value": 536
        }
      },
      {
        "__struct_id": 1,
        "Feat": {
          "type": "word",
          "value": 555
        }
      },
      {
        "__struct_id": 1,
        "Feat": {
          "type": "word",
          "value": 584
        }
      },
      {
        "__struct_id": 1,
        "Feat": {
          "type": "word",
          "value": 592
        }
      },
      {
        "__struct_id": 1,
        "Feat": {
          "type": "word",
          "value": 918
        }
      },
      {
        "__struct_id": 1,
        "Feat": {
          "type": "word",
          "value": 595
        }
      },
      {
        "__struct_id": 1,
        "Feat": {
          "type": "word",
          "value": 640
        }
      },
      {
        "__struct_id": 1,
        "Feat": {
          "type": "word",
          "value": 625
        }
      },
      {
        "__struct_id": 1,
        "Feat": {
          "type": "word",
          "value": 695
        }
      },
      {
        "__struct_id": 1,
        "Feat": {
          "type": "word",
          "value": 391
        }
      },
      {
        "__struct_id": 1,
        "Feat": {
          "type": "word",
          "value": 14
        }
      },
      {
        "__struct_id": 1,
        "Feat": {
          "type": "word",
          "value": 331
        }
      },
      {
        "__struct_id": 1,
        "Feat": {
          "type": "word",
          "value": 330
        }
      },
      {
        "__struct_id": 1,
        "Feat": {
          "type": "word",
          "value": 72
        }
      },
      {
        "__struct_id": 1,
        "Feat": {
          "type": "word",
          "value": 57
        }
      },
      {
        "__struct_id": 1,
        "Feat": {
          "type": "word",
          "value": 20
        }
      },
      {
        "__struct_id": 1,
        "Feat": {
          "type": "word",
          "value": 24
        }
      },
      {
        "__struct_id": 1,
        "Feat": {
          "type": "word",
          "value": 869
        }
      },
      {
        "__struct_id": 1,
        "Feat": {
          "type": "word",
          "value": 26
        }
      },
      {
        "__struct_id": 1,
        "Feat": {
          "type": "word",
          "value": 730
        }
      },
      {
        "__struct_id": 1,
        "Feat": {
          "type": "word",
          "value": 715
        }
      },
      {
        "__struct_id": 1,
        "Feat": {
          "type": "word",
          "value": 747
        }
      },
      {
        "__struct_id": 1,
        "Feat": {
          "type": "word",
          "value": 28
        }
      },
      {
        "__struct_id": 1,
        "Feat": {
          "type": "word",
          "value": 989
        }
      },
      {
        "__struct_id": 1,
        "Feat": {
          "type": "word",
          "value": 988
        }
      },
      {
        "__struct_id": 1,
        "Feat": {
          "type": "word",
          "value": 40
        }
      },
      {
        "__struct_id": 1,
        "Feat": {
          "type": "word",
          "value": 41
        }
      },
      {
        "__struct_id": 1,
        "Feat": {
          "type": "word",
          "value": 110
        }
      },
      {
        "__struct_id": 1,
        "Feat": {
          "type": "word",
          "value": 95
        }
      },
      {
        "__struct_id": 1,
        "Feat": {
          "type": "word",
          "value": 45
        }
      },
      {
        "__struct_id": 1,
        "Feat": {
          "type": "word",
          "value": 46
        }
      },
      {
        "__struct_id": 1,
        "Feat": {
          "type": "word",
          "value": 148
        }
      },
      {
        "__struct_id": 1,
        "Feat": {
          "type": "word",
          "value": 133
        }
      },
      {
        "__struct_id": 1,
        "Feat": {
          "type": "word",
          "value": 867
        }
      }
    ]
  },
  "FirstName": {
    "type": "cexolocstring",
    "value": {
      "0": "<cüz >Bezerker of Baghtru</c>"
    }
  },
  "fortbonus": {
    "type": "short",
    "value": 0
  },
  "Gender": {
    "type": "byte",
    "value": 0
  },
  "GoodEvil": {
    "type": "byte",
    "value": 0
  },
  "HitPoints": {
    "type": "short",
    "value": 4
  },
  "Int": {
    "type": "byte",
    "value": 8
  },
  "Interruptable": {
    "type": "byte",
    "value": 0
  },
  "IsImmortal": {
    "type": "byte",
    "value": 0
  },
  "IsPC": {
    "type": "byte",
    "value": 0
  },
  "LastName": {
    "type": "cexolocstring",
    "value": {
      "0": ""
    }
  },
  "LawfulChaotic": {
    "type": "byte",
    "value": 0
  },
  "Lootable": {
    "type": "byte",
    "value": 0
  },
  "MaxHitPoints": {
    "type": "short",
    "value": 388
  },
  "NaturalAC": {
    "type": "byte",
    "value": 29
  },
  "NoPermDeath": {
    "type": "byte",
    "value": 0
  },
  "PaletteID": {
    "type": "byte",
    "value": 64
  },
  "PerceptionRange": {
    "type": "byte",
    "value": 11
  },
  "Phenotype": {
    "type": "int",
    "value": 0
  },
  "Plot": {
    "type": "byte",
    "value": 0
  },
  "PortraitId": {
    "type": "word",
    "value": 692
  },
  "Race": {
    "type": "byte",
    "value": 14
  },
  "refbonus": {
    "type": "short",
    "value": 0
  },
  "ScriptAttacked": {
    "type": "resref",
    "value": "x2_def_attacked"
  },
  "ScriptDamaged": {
    "type": "resref",
    "value": "x2_def_ondamage"
  },
  "ScriptDeath": {
    "type": "resref",
    "value": "x2_def_ondeath"
  },
  "ScriptDialogue": {
    "type": "resref",
    "value": "x2_def_onconv"
  },
  "ScriptDisturbed": {
    "type": "resref",
    "value": "x2_def_ondisturb"
  },
  "ScriptEndRound": {
    "type": "resref",
    "value": "x2_def_endcombat"
  },
  "ScriptHeartbeat": {
    "type": "resref",
    "value": "x2_def_heartbeat"
  },
  "ScriptOnBlocked": {
    "type": "resref",
    "value": "x2_def_onblocked"
  },
  "ScriptOnNotice": {
    "type": "resref",
    "value": "x2_def_percept"
  },
  "ScriptRested": {
    "type": "resref",
    "value": "x2_def_rested"
  },
  "ScriptSpawn": {
    "type": "resref",
    "value": "x2_def_spawn"
  },
  "ScriptSpellAt": {
    "type": "resref",
    "value": "x2_def_spellcast"
  },
  "ScriptUserDefine": {
    "type": "resref",
    "value": "x2_def_userdef"
  },
  "SkillList": {
    "type": "list",
    "value": [
      {
        "__struct_id": 0,
        "Rank": {
          "type": "byte",
          "value": 0
        }
      },
      {
        "__struct_id": 0,
        "Rank": {
          "type": "byte",
          "value": 0
        }
      },
      {
        "__struct_id": 0,
        "Rank": {
          "type": "byte",
          "value": 0
        }
      },
      {
        "__struct_id": 0,
        "Rank": {
          "type": "byte",
          "value": 65
        }
      },
      {
        "__struct_id": 0,
        "Rank": {
          "type": "byte",
          "value": 0
        }
      },
      {
        "__struct_id": 0,
        "Rank": {
          "type": "byte",
          "value": 0
        }
      },
      {
        "__struct_id": 0,
        "Rank": {
          "type": "byte",
          "value": 82
        }
      },
      {
        "__struct_id": 0,
        "Rank": {
          "type": "byte",
          "value": 0
        }
      },
      {
        "__struct_id": 0,
        "Rank": {
          "type": "byte",
          "value": 0
        }
      },
      {
        "__struct_id": 0,
        "Rank": {
          "type": "byte",
          "value": 0
        }
      },
      {
        "__struct_id": 0,
        "Rank": {
          "type": "byte",
          "value": 4
        }
      },
      {
        "__struct_id": 0,
        "Rank": {
          "type": "byte",
          "value": 0
        }
      },
      {
        "__struct_id": 0,
        "Rank": {
          "type": "byte",
          "value": 0
        }
      },
      {
        "__struct_id": 0,
        "Rank": {
          "type": "byte",
          "value": 0
        }
      },
      {
        "__struct_id": 0,
        "Rank": {
          "type": "byte",
          "value": 0
        }
      },
      {
        "__struct_id": 0,
        "Rank": {
          "type": "byte",
          "value": 0
        }
      },
      {
        "__struct_id": 0,
        "Rank": {
          "type": "byte",
          "value": 0
        }
      },
      {
        "__struct_id": 0,
        "Rank": {
          "type": "byte",
          "value": 60
        }
      },
      {
        "__struct_id": 0,
        "Rank": {
          "type": "byte",
          "value": 0
        }
      },
      {
        "__struct_id": 0,
        "Rank": {
          "type": "byte",
          "value": 0
        }
      },
      {
        "__struct_id": 0,
        "Rank": {
          "type": "byte",
          "value": 0
        }
      },
      {
        "__struct_id": 0,
        "Rank": {
          "type": "byte",
          "value": 0
        }
      },
      {
        "__struct_id": 0,
        "Rank": {
          "type": "byte",
          "value": 0
        }
      },
      {
        "__struct_id": 0,
        "Rank": {
          "type": "byte",
          "value": 0
        }
      },
      {
        "__struct_id": 0,
        "Rank": {
          "type": "byte",
          "value": 0
        }
      },
      {
        "__struct_id": 0,
        "Rank": {
          "type": "byte",
          "value": 0
        }
      },
      {
        "__struct_id": 0,
        "Rank": {
          "type": "byte",
          "value": 0
        }
      },
      {
        "__struct_id": 0,
        "Rank": {
          "type": "byte",
          "value": 0
        }
      }
    ]
  },
  "SoundSetFile": {
    "type": "word",
    "value": 74
  },
  "SpecAbilityList": {
    "type": "list",
    "value": [
      {
        "__struct_id": 4,
        "Spell": {
          "type": "word",
          "value": 199
        },
        "SpellCasterLevel": {
          "type": "byte",
          "value": 0
        },
        "SpellFlags": {
          "type": "byte",
          "value": 1
        }
      },
      {
        "__struct_id": 4,
        "Spell": {
          "type": "word",
          "value": 517
        },
        "SpellCasterLevel": {
          "type": "byte",
          "value": 14
        },
        "SpellFlags": {
          "type": "byte",
          "value": 1
        }
      },
      {
        "__struct_id": 4,
        "Spell": {
          "type": "word",
          "value": 422
        },
        "SpellCasterLevel": {
          "type": "byte",
          "value": 5
        },
        "SpellFlags": {
          "type": "byte",
          "value": 1
        }
      }
    ]
  },
  "StartingPackage": {
    "type": "byte",
    "value": 17
  },
  "Str": {
    "type": "byte",
    "value": 42
  },
  "Subrace": {
    "type": "cexostring",
    "value": ""
  },
  "Tag": {
    "type": "cexostring",
    "value": "czBezerkerofBaghtruc"
  },
  "Tail_New": {
    "type": "dword",
    "value": 0
  },
  "TemplateList": {
    "type": "list",
    "value": []
  },
  "TemplateResRef": {
    "type": "resref",
    "value": "beserkbaghtru"
  },
  "WalkRate": {
    "type": "int",
    "value": 5
  },
  "willbonus": {
    "type": "short",
    "value": 0
  },
  "Wings_New": {
    "type": "dword",
    "value": 0
  },
  "Wis": {
    "type": "byte",
    "value": 14
  }
}
