{
  "__data_type": "UTI ",
  "AddCost": {
    "type": "dword",
    "value": 0
  },
  "ArmorPart_Belt": {
    "type": "byte",
    "value": 0
  },
  "ArmorPart_LBicep": {
    "type": "byte",
    "value": 1
  },
  "ArmorPart_LFArm": {
    "type": "byte",
    "value": 1
  },
  "ArmorPart_LFoot": {
    "type": "byte",
    "value": 3
  },
  "ArmorPart_LHand": {
    "type": "byte",
    "value": 1
  },
  "ArmorPart_LShin": {
    "type": "byte",
    "value": 1
  },
  "ArmorPart_LShoul": {
    "type": "byte",
    "value": 0
  },
  "ArmorPart_LThigh": {
    "type": "byte",
    "value": 1
  },
  "ArmorPart_Neck": {
    "type": "byte",
    "value": 1
  },
  "ArmorPart_Pelvis": {
    "type": "byte",
    "value": 1
  },
  "ArmorPart_RBicep": {
    "type": "byte",
    "value": 1
  },
  "ArmorPart_RFArm": {
    "type": "byte",
    "value": 1
  },
  "ArmorPart_RFoot": {
    "type": "byte",
    "value": 3
  },
  "ArmorPart_RHand": {
    "type": "byte",
    "value": 1
  },
  "ArmorPart_Robe": {
    "type": "byte",
    "value": 4
  },
  "ArmorPart_RShin": {
    "type": "byte",
    "value": 1
  },
  "ArmorPart_RShoul": {
    "type": "byte",
    "value": 0
  },
  "ArmorPart_RThigh": {
    "type": "byte",
    "value": 1
  },
  "ArmorPart_Torso": {
    "type": "byte",
    "value": 1
  },
  "BaseItem": {
    "type": "int",
    "value": 16
  },
  "Charges": {
    "type": "byte",
    "value": 0
  },
  "Cloth1Color": {
    "type": "byte",
    "value": 159
  },
  "Cloth2Color": {
    "type": "byte",
    "value": 159
  },
  "Comment": {
    "type": "cexostring",
    "value": ""
  },
  "Cost": {
    "type": "dword",
    "value": 98209
  },
  "Cursed": {
    "type": "byte",
    "value": 0
  },
  "DescIdentified": {
    "type": "cexolocstring",
    "value": {
      "0": "Monks of the Sun Soul Order believe that they each harbor a small fragment of the sun's divine essence, long absent from the Realms. Brothers and sisters of the Order of the Sun Soul are trained to tap into the \"spiritual light\" within -- a tradition that developed during Amaunator's slow decline -- and manifest it externally. The monks are loosely affiliated with the faiths of Lathander, Selûne, and Sune, and they share many common concerns with those churches. Staunch opponents of darkness, evil, and chaos, the Sun Soul monks serve as crusaders against churches of evil deities, defenders of the common folk, and protectors of sites sacred to deities of light and good.  Unlike most other monastic orders, the Sun Soul monks are free to train in one other profession, as long as thier devotion to it does not supercede thier monk studies."
    }
  },
  "Description": {
    "type": "cexolocstring",
    "value": {
      "0": ""
    }
  },
  "Identified": {
    "type": "byte",
    "value": 1
  },
  "Leather1Color": {
    "type": "byte",
    "value": 37
  },
  "Leather2Color": {
    "type": "byte",
    "value": 37
  },
  "LocalizedName": {
    "type": "cexolocstring",
    "value": {
      "0": " Robes of the Sun Soul"
    }
  },
  "Metal1Color": {
    "type": "byte",
    "value": 92
  },
  "Metal2Color": {
    "type": "byte",
    "value": 92
  },
  "PaletteID": {
    "type": "byte",
    "value": 5
  },
  "Plot": {
    "type": "byte",
    "value": 1
  },
  "PropertiesList": {
    "type": "list",
    "value": [
      {
        "__struct_id": 0,
        "ChanceAppear": {
          "type": "byte",
          "value": 100
        },
        "CostTable": {
          "type": "byte",
          "value": 1
        },
        "CostValue": {
          "type": "word",
          "value": 1
        },
        "Param1": {
          "type": "byte",
          "value": 255
        },
        "Param1Value": {
          "type": "byte",
          "value": 0
        },
        "PropertyName": {
          "type": "word",
          "value": 0
        },
        "Subtype": {
          "type": "word",
          "value": 5
        }
      },
      {
        "__struct_id": 0,
        "ChanceAppear": {
          "type": "byte",
          "value": 100
        },
        "CostTable": {
          "type": "byte",
          "value": 1
        },
        "CostValue": {
          "type": "word",
          "value": 2
        },
        "Param1": {
          "type": "byte",
          "value": 255
        },
        "Param1Value": {
          "type": "byte",
          "value": 0
        },
        "PropertyName": {
          "type": "word",
          "value": 0
        },
        "Subtype": {
          "type": "word",
          "value": 4
        }
      },
      {
        "__struct_id": 0,
        "ChanceAppear": {
          "type": "byte",
          "value": 100
        },
        "CostTable": {
          "type": "byte",
          "value": 2
        },
        "CostValue": {
          "type": "word",
          "value": 3
        },
        "Param1": {
          "type": "byte",
          "value": 255
        },
        "Param1Value": {
          "type": "byte",
          "value": 0
        },
        "PropertyName": {
          "type": "word",
          "value": 1
        },
        "Subtype": {
          "type": "word",
          "value": 0
        }
      },
      {
        "__struct_id": 0,
        "ChanceAppear": {
          "type": "byte",
          "value": 100
        },
        "CostTable": {
          "type": "byte",
          "value": 2
        },
        "CostValue": {
          "type": "word",
          "value": 5
        },
        "Param1": {
          "type": "byte",
          "value": 255
        },
        "Param1Value": {
          "type": "byte",
          "value": 0
        },
        "PropertyName": {
          "type": "word",
          "value": 4
        },
        "Subtype": {
          "type": "word",
          "value": 24
        }
      },
      {
        "__struct_id": 0,
        "ChanceAppear": {
          "type": "byte",
          "value": 100
        },
        "CostTable": {
          "type": "byte",
          "value": 7
        },
        "CostValue": {
          "type": "word",
          "value": 2
        },
        "Param1": {
          "type": "byte",
          "value": 255
        },
        "Param1Value": {
          "type": "byte",
          "value": 0
        },
        "PropertyName": {
          "type": "word",
          "value": 23
        },
        "Subtype": {
          "type": "word",
          "value": 10
        }
      },
      {
        "__struct_id": 0,
        "ChanceAppear": {
          "type": "byte",
          "value": 100
        },
        "CostTable": {
          "type": "byte",
          "value": 18
        },
        "CostValue": {
          "type": "word",
          "value": 4
        },
        "Param1": {
          "type": "byte",
          "value": 9
        },
        "Param1Value": {
          "type": "byte",
          "value": 1
        },
        "PropertyName": {
          "type": "word",
          "value": 44
        },
        "Subtype": {
          "type": "word",
          "value": 0
        }
      },
      {
        "__struct_id": 0,
        "ChanceAppear": {
          "type": "byte",
          "value": 100
        },
        "CostTable": {
          "type": "byte",
          "value": 0
        },
        "CostValue": {
          "type": "word",
          "value": 0
        },
        "Param1": {
          "type": "byte",
          "value": 255
        },
        "Param1Value": {
          "type": "byte",
          "value": 0
        },
        "PropertyName": {
          "type": "word",
          "value": 63
        },
        "Subtype": {
          "type": "word",
          "value": 5
        }
      },
      {
        "__struct_id": 0,
        "ChanceAppear": {
          "type": "byte",
          "value": 100
        },
        "CostTable": {
          "type": "byte",
          "value": 0
        },
        "CostValue": {
          "type": "word",
          "value": 0
        },
        "Param1": {
          "type": "byte",
          "value": 255
        },
        "Param1Value": {
          "type": "byte",
          "value": 0
        },
        "PropertyName": {
          "type": "word",
          "value": 65
        },
        "Subtype": {
          "type": "word",
          "value": 0
        }
      },
      {
        "__struct_id": 0,
        "ChanceAppear": {
          "type": "byte",
          "value": 100
        },
        "CostTable": {
          "type": "byte",
          "value": 0
        },
        "CostValue": {
          "type": "word",
          "value": 0
        },
        "Param1": {
          "type": "byte",
          "value": 255
        },
        "Param1Value": {
          "type": "byte",
          "value": 0
        },
        "PropertyName": {
          "type": "word",
          "value": 65
        },
        "Subtype": {
          "type": "word",
          "value": 1
        }
      }
    ]
  },
  "StackSize": {
    "type": "word",
    "value": 1
  },
  "Stolen": {
    "type": "byte",
    "value": 0
  },
  "Tag": {
    "type": "cexostring",
    "value": "RobesoftheSunSoul"
  },
  "TemplateResRef": {
    "type": "resref",
    "value": "robesofthesunsou"
  },
  "xArmorPart_Belt": {
    "type": "word",
    "value": 0
  },
  "xArmorPart_LBice": {
    "type": "word",
    "value": 1
  },
  "xArmorPart_LFArm": {
    "type": "word",
    "value": 1
  },
  "xArmorPart_LFoot": {
    "type": "word",
    "value": 3
  },
  "xArmorPart_LHand": {
    "type": "word",
    "value": 1
  },
  "xArmorPart_LShin": {
    "type": "word",
    "value": 1
  },
  "xArmorPart_LShou": {
    "type": "word",
    "value": 0
  },
  "xArmorPart_LThig": {
    "type": "word",
    "value": 1
  },
  "xArmorPart_Neck": {
    "type": "word",
    "value": 1
  },
  "xArmorPart_Pelvi": {
    "type": "word",
    "value": 1
  },
  "xArmorPart_RBice": {
    "type": "word",
    "value": 1
  },
  "xArmorPart_RFArm": {
    "type": "word",
    "value": 1
  },
  "xArmorPart_RFoot": {
    "type": "word",
    "value": 3
  },
  "xArmorPart_RHand": {
    "type": "word",
    "value": 1
  },
  "xArmorPart_Robe": {
    "type": "word",
    "value": 4
  },
  "xArmorPart_RShin": {
    "type": "word",
    "value": 1
  },
  "xArmorPart_RShou": {
    "type": "word",
    "value": 0
  },
  "xArmorPart_RThig": {
    "type": "word",
    "value": 1
  },
  "xArmorPart_Torso": {
    "type": "word",
    "value": 1
  }
}
